wamu/__init__.py
wamu/distance.py
wamu/pressure.py
wamu/quantity.py
wamu/rate.py
wamu/temperature.py
wamu/velocity.py
wamu/volume.py
wamu/weight.py
wamu-0.3.5.dist-info/METADATA
wamu-0.3.5.dist-info/WHEEL
wamu-0.3.5.dist-info/licenses/LICENSE
wamu-0.3.5.dist-info/RECORD
