Metadata-Version: 2.4
Name: wamu
Version: 0.3.5
Summary: Utilities for working with Weights & Measures in Python
Author-email: jheddings <jheddings@gmail.com>
License-Expression: MIT
License-File: LICENSE
Requires-Python: <4,>=3.12
Requires-Dist: deprecation<3,>=2.1.0
